humor_langs/__init__.py
humor_langs/main_trans.py
humor_langs-1.0.1.dist-info/LICENSE
humor_langs-1.0.1.dist-info/METADATA
humor_langs-1.0.1.dist-info/WHEEL
humor_langs-1.0.1.dist-info/top_level.txt
humor_langs-1.0.1.dist-info/RECORD
