Metadata-Version: 2.1
Name: humor_langs
Version: 1.0.1
Summary: Translate your string to humorous text!
Home-page: https://github.com/Makiyu-py/humor_langs
Author: Makiyu
Author-email: 73825066+Makiyu-py@users.noreply.github.com
License: MIT
Keywords: Humor owo translate copypasta emojis
Platform: UNKNOWN
Classifier: Development Status :: 5 - Production/Stable
Classifier: License :: OSI Approved :: MIT License
Classifier: Intended Audience :: Developers
Classifier: Intended Audience :: End Users/Desktop
Classifier: Programming Language :: Python :: 3.6
Classifier: Programming Language :: Python :: 3.7
Classifier: Programming Language :: Python :: 3.8
Classifier: Programming Language :: Python :: 3.9
Classifier: Topic :: Games/Entertainment
Requires-Python: >=3.6.0
License-File: LICENSE
